jupyterlab_sql_explorer/__init__.py
jupyterlab_sql_explorer/_version.py
jupyterlab_sql_explorer/comments.py
jupyterlab_sql_explorer/comments_db.py
jupyterlab_sql_explorer/const.py
jupyterlab_sql_explorer/db.py
jupyterlab_sql_explorer/engine.py
jupyterlab_sql_explorer/handlers.py
jupyterlab_sql_explorer/serializer.py
jupyterlab_sql_explorer/task.py
jupyterlab_sql_explorer/tests/__init__.py
jupyterlab_sql_explorer/tests/t_mysql.py
jupyterlab_sql_explorer/tests/test_comments.py
jupyterlab_sql_explorer/tests/test_handlers.py
jupyterlab_sql_explorer/tests/test_sqlite.py
jupyterlab_sql_explorer/tests/test_utils.py
jupyterlab_sql_explorer-0.2.1.data/data/etc/jupyter/jupyter_notebook_config.d/jupyterlab-sql-explorer.json
jupyterlab_sql_explorer-0.2.1.data/data/etc/jupyter/jupyter_server_config.d/jupyterlab-sql-explorer.json
jupyterlab_sql_explorer-0.2.1.data/data/share/jupyter/labextensions/jupyterlab-sql-explorer/build_log.json
jupyterlab_sql_explorer-0.2.1.data/data/share/jupyter/labextensions/jupyterlab-sql-explorer/package.json
jupyterlab_sql_explorer-0.2.1.data/data/share/jupyter/labextensions/jupyterlab-sql-explorer/schemas/jupyterlab-sql-explorer/package.json.orig
jupyterlab_sql_explorer-0.2.1.data/data/share/jupyter/labextensions/jupyterlab-sql-explorer/schemas/jupyterlab-sql-explorer/plugin.json
jupyterlab_sql_explorer-0.2.1.data/data/share/jupyter/labextensions/jupyterlab-sql-explorer/static/lib_index_js.f775090c89d3b6510a9e.js
jupyterlab_sql_explorer-0.2.1.data/data/share/jupyter/labextensions/jupyterlab-sql-explorer/static/lib_index_js.f775090c89d3b6510a9e.js.map
jupyterlab_sql_explorer-0.2.1.data/data/share/jupyter/labextensions/jupyterlab-sql-explorer/static/remoteEntry.a6ec51bb86feab5ddc79.js
jupyterlab_sql_explorer-0.2.1.data/data/share/jupyter/labextensions/jupyterlab-sql-explorer/static/remoteEntry.a6ec51bb86feab5ddc79.js.map
jupyterlab_sql_explorer-0.2.1.data/data/share/jupyter/labextensions/jupyterlab-sql-explorer/static/style.js
jupyterlab_sql_explorer-0.2.1.dist-info/METADATA
jupyterlab_sql_explorer-0.2.1.dist-info/WHEEL
jupyterlab_sql_explorer-0.2.1.dist-info/licenses/LICENSE
jupyterlab_sql_explorer-0.2.1.dist-info/RECORD
